icinga2_api/__init__.py
icinga2_api/api.py
icinga2py-0.1.2.dist-info/METADATA
icinga2py-0.1.2.dist-info/WHEEL
icinga2py-0.1.2.dist-info/top_level.txt
icinga2py-0.1.2.dist-info/RECORD
